<?xml version="1.0" encoding="iso-8859-1"?>
<TestCase version="13.45">
    <UseCase>EXEC_SCRIPT</UseCase>
    <Description>Test case Platform - Sensors</Description>
    <b2bIteration>1</b2bIteration>
    <b2bContinuousMode>True</b2bContinuousMode>
    <TcExpectedResult>PASS</TcExpectedResult>
    <Parameters>
        <Parameter>
            <Name>SCRIPT_PATH</Name>
            <Value>scripts/halctl_sensors.py</Value>
        </Parameter>
            <Parameter>
            <Name>sensors_module_name</Name>
            <Value>IIO sensors HAL</Value>
        </Parameter>
        <Parameter>
            <Name>sensors_module_author</Name>
            <Value>Intel</Value>
        </Parameter>
    </Parameters>
</TestCase>
