<?xml version="1.0" ?>
<TestCase>
    <TcExpectedResult>PASS</TcExpectedResult>
    <Parameters/>
    <Discription>
Check Power Management module auto-detection
&lt;br /&gt;Platform - Power Management
</Discription>
    <Parameters/>
    <UseCase>PY_UNIT</UseCase>
    <Parameters/>
    <b2bContinuousMode>True</b2bContinuousMode>
    <Parameters/>
    <b2bIteration>1</b2bIteration>
    <Parameters>
        <Parameter>
            <Name>TEST_DATA_ROOT</Name>
            <Value>testplan/IRDA_Auto_Detect</Value>
        </Parameter>
        <Parameter>
            <Name>TEST_CASE</Name>
            <Value>tests.IRDA_Auto_Detect.AutoDetect.check_halctl_platform_power.Check_Platform_Power.testCheck_Platform_Power</Value>
        </Parameter>
    </Parameters>
</TestCase>
