<?xml version="1.0" encoding="iso-8859-1"?>
<TestCase>
    <ClassName>acs_test_scripts.UseCase.OTC.Performance.LIVE_PERFMEAS_VIDEO_RECORDING_FPS.VideoRecordingFPS</ClassName>
    <Description>Video recording test</Description>
    <b2bIteration>1</b2bIteration>
    <b2bContinuousMode>True</b2bContinuousMode>
    <TcExpectedResult>PASS</TcExpectedResult>
    <Parameters>
        <Parameter>
            <Name>TIMEOUT</Name>
            <Value>120</Value>
        </Parameter>
        <Parameter>
            <Name>ARGUMENTS</Name>
            <Value>UIAUTOMATOR/Performance.jar</Value>
        </Parameter>
        <Parameter>
            <Name>MEASURE_NB</Name>
            <Value>2</Value>
        </Parameter>
        <Parameter>
            <Name>SYSDEBUG_MODULES</Name>
            <Value></Value>
        </Parameter>
    </Parameters>
</TestCase>
